sketchfab/__init__.py
sketchfab/api.py
sketchfab/clt.py
sketchfab/models.py
sketchfab-0.0.8.data/scripts/sketchfab
sketchfab-0.0.8.dist-info/METADATA
sketchfab-0.0.8.dist-info/WHEEL
sketchfab-0.0.8.dist-info/top_level.txt
sketchfab-0.0.8.dist-info/RECORD
