Metadata-Version: 2.1
Name: sketchfab
Version: 0.0.8
Summary: Sketchfab client
Home-page: https://github.com/habx/lib-py-sketchfab
Author: Florent Clairambault
Author-email: florent@habx.fr
License: MIT
Project-URL: Bug Reports, https://github.com/habx/lib-py-sketchfab/issues
Project-URL: Source, https://github.com/habx/lib-py-sketchfab
Keywords: sketchfab 3d-model client-library development
Platform: UNKNOWN
Classifier: License :: OSI Approved :: MIT License
Classifier: Programming Language :: Python :: 3
Classifier: Programming Language :: Python :: 3.7
Classifier: Topic :: Software Development :: Libraries :: Python Modules
Classifier: Topic :: Multimedia :: Graphics :: 3D Modeling
Classifier: Topic :: Multimedia :: Graphics :: 3D Rendering
Requires-Python: >=3.7
Requires-Dist: requests (==2.22.0)
Requires-Dist: urllib3
Provides-Extra: dev
Requires-Dist: pdoc3 ; extra == 'dev'
